ACO_TSP/__init__.py
ACO_TSP/main.py
aco_tsp-0.2.dist-info/METADATA
aco_tsp-0.2.dist-info/WHEEL
aco_tsp-0.2.dist-info/top_level.txt
aco_tsp-0.2.dist-info/RECORD
