Metadata-Version: 2.1
Name: aco_tsp
Version: 0.2
Requires-Dist: numpy>=2.2.6
